mjango/__init__.py
mjango/db.py
mjango/exceptions.py
mjango/expressions.py
mjango/manager.py
mjango/models.py
mjango/operators.py
mjango/query.py
mjango/settings.py
mjango/mongodb/__init__.py
mjango/mongodb/backends.py
mjango/mongodb/compilers.py
mjango-0.2.3.dist-info/LICENSE
mjango-0.2.3.dist-info/WHEEL
mjango-0.2.3.dist-info/METADATA
mjango-0.2.3.dist-info/RECORD
